RsCMPX_Base/RsCMPX_Base.py
RsCMPX_Base/__init__.py
RsCMPX_Base/enums.py
RsCMPX_Base/repcap.py
RsCMPX_Base/CustomFiles/__init__.py
RsCMPX_Base/CustomFiles/events.py
RsCMPX_Base/CustomFiles/reliability.py
RsCMPX_Base/CustomFiles/utilities.py
RsCMPX_Base/Implementations/FirmwareUpdate.py
RsCMPX_Base/Implementations/Get.py
RsCMPX_Base/Implementations/GlobalClearStatus.py
RsCMPX_Base/Implementations/GlobalWait.py
RsCMPX_Base/Implementations/GotoLocal.py
RsCMPX_Base/Implementations/MacroCreate.py
RsCMPX_Base/Implementations/Procedure.py
RsCMPX_Base/Implementations/RecallState.py
RsCMPX_Base/Implementations/SaveState.py
RsCMPX_Base/Implementations/TriggerInvoke.py
RsCMPX_Base/Implementations/Unit.py
RsCMPX_Base/Implementations/__init__.py
RsCMPX_Base/Implementations/Add/__init__.py
RsCMPX_Base/Implementations/Add/System/__init__.py
RsCMPX_Base/Implementations/Add/System/Attenuation/__init__.py
RsCMPX_Base/Implementations/Add/System/Attenuation/CorrectionTable/Globale.py
RsCMPX_Base/Implementations/Add/System/Attenuation/CorrectionTable/Tenvironment.py
RsCMPX_Base/Implementations/Add/System/Attenuation/CorrectionTable/__init__.py
RsCMPX_Base/Implementations/Add/Tenvironment/__init__.py
RsCMPX_Base/Implementations/Add/Tenvironment/Spath/__init__.py
RsCMPX_Base/Implementations/Add/Tenvironment/Spath/CorrectionTable/Rx.py
RsCMPX_Base/Implementations/Add/Tenvironment/Spath/CorrectionTable/Tx.py
RsCMPX_Base/Implementations/Add/Tenvironment/Spath/CorrectionTable/__init__.py
RsCMPX_Base/Implementations/Base/__init__.py
RsCMPX_Base/Implementations/Base/Buffer/LineCount.py
RsCMPX_Base/Implementations/Base/Buffer/__init__.py
RsCMPX_Base/Implementations/Base/Correction/__init__.py
RsCMPX_Base/Implementations/Base/Correction/IfEqualizer/State.py
RsCMPX_Base/Implementations/Base/Correction/IfEqualizer/__init__.py
RsCMPX_Base/Implementations/Base/Correction/IfEqualizer/Slot/RxFilter.py
RsCMPX_Base/Implementations/Base/Correction/IfEqualizer/Slot/TxFilter.py
RsCMPX_Base-5.0.60.dist-info/METADATA
RsCMPX_Base-5.0.60.dist-info/WHEEL
RsCMPX_Base-5.0.60.dist-info/top_level.txt
RsCMPX_Base-5.0.60.dist-info/RECORD
